Workbook
Name Slicer_Month_Name: #N/A
Name Slicer_Product: #N/A
Name Slicer_Salesperson: #N/A

Sheet raw_data
A1: Date | B1: Region | C1: Product | D1: Category | E1: Salesperson | F1: Units | G1: Price | H1: Customer_Name | I1: Customer_City | J1: Customer_Tier
A2: 45296 | B2: North | C2: Laptop | D2: Electronics | E2: John | F2: 5 | G2: 800 | H2: Acme Corp | I2: New York | J2: Enterprise
A3: 45303 | B3: South | C3: Mouse | D3: Accessories | E3: Sarah | F3: 12 | G3: 25 | H3: Beta LLC | I3: Miami | J3: Small
A4: 45309 | B4: East | C4: Keyboard | D4: Accessories | E4: Mike | F4: 8 | G4: 45 | H4: Gamma Inc | I4: Boston | J4: Medium
A5: 45316 | B5: West | C5: Monitor | D5: Electronics | E5: Lisa | F5: 3 | G5: 300 | H5: Delta Co | I5: Los Angeles | J5: Enterprise
A6: 45324 | B6: North | C6: Laptop | D6: Electronics | E6: John | F6: 2 | G6: 800 | H6: Acme Corp | I6: New York | J6: Enterprise
A7: 45331 | B7: South | C7: Mouse | D7: Accessories | E7: Sarah | F7: 15 | G7: 25 | H7: Beta LLC | I7: Miami | J7: Small
A8: 45338 | B8: East | C8: Headphones | D8: Accessories | E8: Mike | F8: 10 | G8: 80 | H8: Gamma Inc | I8: Boston | J8: Medium
A9: 45345 | B9: West | C9: Monitor | D9: Electronics | E9: Lisa | F9: 4 | G9: 300 | H9: Delta Co | I9: Los Angeles | J9: Enterprise
A10: 45353 | B10: North | C10: Tablet | D10: Electronics | E10: John | F10: 6 | G10: 400 | H10: Epsilon | I10: New York | J10: Medium
A11: 45360 | B11: South | C11: Keyboard | D11: Accessories | E11: Sarah | F11: 7 | G11: 45 | H11: Beta LLC | I11: Miami | J11: Small
A12: 45367 | B12: East | C12: Laptop | D12: Electronics | E12: Mike | F12: 4 | G12: 800 | H12: Gamma Inc | I12: Boston | J12: Medium
A13: 45374 | B13: West | C13: Headphones | D13: Accessories | E13: Lisa | F13: 8 | G13: 80 | H13: Delta Co | I13: Los Angeles | J13: Enterprise
... A31: 45512 | B31: South | C31: Tablet | D31: Electronics | E31: Sarah | F31: 2 | G31: 400 | H31: Beta LLC | I31: Miami | J31: Small

Sheet cleaned_data
A1: Date | B1: Region | C1: Product | D1: Category | E1: Salesperson | F1: Units | G1: Price | H1: Customer_Name | I1: Customer_City | J1: Customer_Tier | K1: Total_Sales | L1: Profit | M1: Discount_Eligible | N1: Commission | O1: Quarter | P1: Month_Name
A2: 45296 | B2: North | C2: Laptop | D2: Electronics | E2: John | F2: 5 | G2: 800 | H2: Acme Corp | I2: New York | J2: Enterprise | K2: =F2*G2 -> 4000 | L2: =IF(D2="Electronics", K2*0.4, K2*0.3) -> 1600 | M2: =IF(K2>2000, "Yes", "No") -> Yes | N2: =L2*0.1 -> 160 | O2: ="Q"&ROUNDUP(MONTH(A2)/3,0) -> Q1 | P2: =TEXT(A2,"MMMM") -> January
A3: 45303 | B3: South | C3: Mouse | D3: Accessories | E3: Sarah | F3: 12 | G3: 25 | H3: Beta LLC | I3: Miami | J3: Small | K3: =F3*G3 -> 300 | L3: =IF(D3="Electronics", K3*0.4, K3*0.3) -> 90 | M3: =IF(K3>2000, "Yes", "No") -> No | N3: =L3*0.1 -> 9 | O3: ="Q"&ROUNDUP(MONTH(A3)/3,0) -> Q1 | P3: =TEXT(A3,"MMMM") -> January
A4: 45309 | B4: East | C4: Keyboard | D4: Accessories | E4: Mike | F4: 8 | G4: 45 | H4: Gamma Inc | I4: Boston | J4: Medium | K4: =F4*G4 -> 360 | L4: =IF(D4="Electronics", K4*0.4, K4*0.3) -> 108 | M4: =IF(K4>2000, "Yes", "No") -> No | N4: =L4*0.1 -> 10.8 | O4: ="Q"&ROUNDUP(MONTH(A4)/3,0) -> Q1 | P4: =TEXT(A4,"MMMM") -> January
A5: 45316 | B5: West | C5: Monitor | D5: Electronics | E5: Lisa | F5: 3 | G5: 300 | H5: Delta Co | I5: Los Angeles | J5: Enterprise | K5: =F5*G5 -> 900 | L5: =IF(D5="Electronics", K5*0.4, K5*0.3) -> 360 | M5: =IF(K5>2000, "Yes", "No") -> No | N5: =L5*0.1 -> 36 | O5: ="Q"&ROUNDUP(MONTH(A5)/3,0) -> Q1 | P5: =TEXT(A5,"MMMM") -> January
A6: 45324 | B6: North | C6: Laptop | D6: Electronics | E6: John | F6: 2 | G6: 800 | H6: Acme Corp | I6: New York | J6: Enterprise | K6: =F6*G6 -> 1600 | L6: =IF(D6="Electronics", K6*0.4, K6*0.3) -> 640 | M6: =IF(K6>2000, "Yes", "No") -> No | N6: =L6*0.1 -> 64 | O6: ="Q"&ROUNDUP(MONTH(A6)/3,0) -> Q1 | P6: =TEXT(A6,"MMMM") -> February
A7: 45331 | B7: South | C7: Mouse | D7: Accessories | E7: Sarah | F7: 15 | G7: 25 | H7: Beta LLC | I7: Miami | J7: Small | K7: =F7*G7 -> 375 | L7: =IF(D7="Electronics", K7*0.4, K7*0.3) -> 112.5 | M7: =IF(K7>2000, "Yes", "No") -> No | N7: =L7*0.1 -> 11.25 | O7: ="Q"&ROUNDUP(MONTH(A7)/3,0) -> Q1 | P7: =TEXT(A7,"MMMM") -> February
A8: 45338 | B8: East | C8: Headphones | D8: Accessories | E8: Mike | F8: 10 | G8: 80 | H8: Gamma Inc | I8: Boston | J8: Medium | K8: =F8*G8 -> 800 | L8: =IF(D8="Electronics", K8*0.4, K8*0.3) -> 240 | M8: =IF(K8>2000, "Yes", "No") -> No | N8: =L8*0.1 -> 24 | O8: ="Q"&ROUNDUP(MONTH(A8)/3,0) -> Q1 | P8: =TEXT(A8,"MMMM") -> February
A9: 45345 | B9: West | C9: Monitor | D9: Electronics | E9: Lisa | F9: 4 | G9: 300 | H9: Delta Co | I9: Los Angeles | J9: Enterprise | K9: =F9*G9 -> 1200 | L9: =IF(D9="Electronics", K9*0.4, K9*0.3) -> 480 | M9: =IF(K9>2000, "Yes", "No") -> No | N9: =L9*0.1 -> 48 | O9: ="Q"&ROUNDUP(MONTH(A9)/3,0) -> Q1 | P9: =TEXT(A9,"MMMM") -> February
A10: 45353 | B10: North | C10: Tablet | D10: Electronics | E10: John | F10: 6 | G10: 400 | H10: Epsilon | I10: New York | J10: Medium | K10: =F10*G10 -> 2400 | L10: =IF(D10="Electronics", K10*0.4, K10*0.3) -> 960 | M10: =IF(K10>2000, "Yes", "No") -> Yes | N10: =L10*0.1 -> 96 | O10: ="Q"&ROUNDUP(MONTH(A10)/3,0) -> Q1 | P10: =TEXT(A10,"MMMM") -> March
A11: 45360 | B11: South | C11: Keyboard | D11: Accessories | E11: Sarah | F11: 7 | G11: 45 | H11: Beta LLC | I11: Miami | J11: Small | K11: =F11*G11 -> 315 | L11: =IF(D11="Electronics", K11*0.4, K11*0.3) -> 94.5 | M11: =IF(K11>2000, "Yes", "No") -> No | N11: =L11*0.1 -> 9.45 | O11: ="Q"&ROUNDUP(MONTH(A11)/3,0) -> Q1 | P11: =TEXT(A11,"MMMM") -> March
A12: 45367 | B12: East | C12: Laptop | D12: Electronics | E12: Mike | F12: 4 | G12: 800 | H12: Gamma Inc | I12: Boston | J12: Medium | K12: =F12*G12 -> 3200 | L12: =IF(D12="Electronics", K12*0.4, K12*0.3) -> 1280 | M12: =IF(K12>2000, "Yes", "No") -> Yes | N12: =L12*0.1 -> 128 | O12: ="Q"&ROUNDUP(MONTH(A12)/3,0) -> Q1 | P12: =TEXT(A12,"MMMM") -> March
A13: 45374 | B13: West | C13: Headphones | D13: Accessories | E13: Lisa | F13: 8 | G13: 80 | H13: Delta Co | I13: Los Angeles | J13: Enterprise | K13: =F13*G13 -> 640 | L13: =IF(D13="Electronics", K13*0.4, K13*0.3) -> 192 | M13: =IF(K13>2000, "Yes", "No") -> No | N13: =L13*0.1 -> 19.2 | O13: ="Q"&ROUNDUP(MONTH(A13)/3,0) -> Q1 | P13: =TEXT(A13,"MMMM") -> March
... A31: 45512 | B31: South | C31: Tablet | D31: Electronics | E31: Sarah | F31: 2 | G31: 400 | H31: Beta LLC | I31: Miami | J31: Small | K31: =F31*G31 -> 800 | L31: =IF(D31="Electronics", K31*0.4, K31*0.3) -> 320 | M31: =IF(K31>2000, "Yes", "No") -> No | N31: =L31*0.1 -> 32 | O31: ="Q"&ROUNDUP(MONTH(A31)/3,0) -> Q3 | P31: =TEXT(A31,"MMMM") -> August

Sheet KPIcalculations
A1: KPI CALCULATIONS
A2: Metric | B2: Value | C2: Formula Explanation
A3: Total Revenue | B3: =SUM(cleaned_data!K:K) -> 34090 | C3: Adds up all sales amounts
A4: Total Profit | B4: =SUM(cleaned_data!L:L) -> 12907 | C4: Adds up all profit amounts
A5: Total Units Sold | B5: =SUM(cleaned_data!F:F) -> 236 | C5: Adds up all unit quantities
A6: Average Order Value | B6: =B3/COUNT(cleaned_data!F2:F31) -> 1136.3333 | C6: Total Revenue ÷ Number of sales
A7: Total Customers | B7: =COUNTA(_xlfn.UNIQUE(cleaned_data!H2:H31)) -> 5 | C7: Counts unique customer names
A8: Top Product by Revenue | B8: =INDEX(cleaned_data!C:C, MATCH(MAX(cleaned_data!K:K), cleaned_data!K:K, 0)) -> Laptop | C8: Finds product with highest total sales
A9: Top Salesperson | B9: {=INDEX(cleaned_data!E:E, MATCH(MAX(SUMIF(cleaned_data!E:E, cleaned_data!E:E, cleaned_data!K:K)), SUMIF(cleaned_data!E:E, cleaned_data!E:E, cleaned_data!K:K), 0))} -> John | C9: Finds salesperson with highest total sales
A10: Best Region by Revenue | B10: {=INDEX(cleaned_data!B:B, MATCH(MAX(SUMIF(cleaned_data!B:B, cleaned_data!B:B, cleaned_data!K:K)), SUMIF(cleaned_data!B:B, cleaned_data!B:B, cleaned_data!K:K), 0))} -> North | C10: Finds region with highest total sales
A11: Performance Status | B11: =IF(B3>150000, "Above Target", "Meeting Target") -> Meeting Target | C11: Checks if revenue exceeds target

Sheet Pivot_Table
A1: Row Labels | B1: Count of Customer_Name | C1: Sum of Total_Sales
A2: Enterprise | B2: 0.4 | C2: 15040
A3: Medium | B3: 0.33333333 | C3: 13440
A4: Small | B4: 0.26666667 | C4: 5610
A5: Grand Total | B5: 1 | C5: 34090
A8: Row Labels | B8: Sum of Total_Sales | C8: Sum of Total_Sales2
A9: January | B9: 5560 | C9: 0.16309768
A10: February | B10: 3975 | C10: 0.11660311
A11: March | B11: 6555 | C11: 0.19228513
A12: April | B12: 4700 | C12: 0.13787034
A13: May | B13: 3040 | C13: 0.089175711
A14: June | B14: 4825 | C14: 0.14153711
A15: July | B15: 3885 | C15: 0.11396304
A16: August | B16: 1550 | C16: 0.045467879
A17: Grand Total | B17: 34090 | C17: 1
A20: Sum of Total_Sales | B20: Column Labels
A21: Row Labels | B21: East | C21: North | D21: South | E21: West | F21: Grand Total
A22: Accessories | B22: 1610 | C22: 2480 | D22: 1710 | E22: 1490 | F22: 7290
A23: Electronics | B23: 8200 | C23: 8600 | D23: 3900 | E23: 6100 | F23: 26800
A24: Grand Total | B24: 9810 | C24: 11080 | D24: 5610 | E24: 7590 | F24: 34090
A27: Row Labels | B27: Sum of Total_Sales | C27: Sum of Commission | D27: Sum of Units
A28: John | B28: 11080 | C28: 418.4 | D28: 83
A29: Mike | B29: 9810 | C29: 376.3 | D29: 50
A30: Lisa | B30: 7590 | C30: 288.7 | D30: 52
A31: Sarah | B31: 5610 | C31: 207.3 | D31: 51
A32: Grand Total | B32: 34090 | C32: 1290.7 | D32: 236

Sheet Insight&Recommendation
A1: KEY INSIGHTS & RECOMMENDATIONS
A3: SALES INSIGHTS:
A4: Total Revenue: $34,090
A5: Total Profit: $10,227
A6: Average Order Value: $1,136
A7: Total Units Sold: 236 units
A9: TOP PERFORMERS:
A10: Top Salesperson: John ($11,080)
A11: Best Region: North ($11,080)
A12: Top Product: Laptop
A14: CUSTOMER INSIGHTS:
A15: Enterprise customers (40% of base) drive $15,040 in revenue
... A29: 5. Run promotions during slower months (May, August)
